{
	"auth": {
		"signin": "Login",
		"signup": "Sign Up",
		"logout": "Log Out",
		"welcomeback": "Welcome back",
		"donthaveaccount": "Don't have a account",
		"haveaccount": "Already have an account",
		"form": {
			"enteremail": "Enter email address",
			"enterpassword": "Enter password",
			"enterconfirmpassword": "Enter confirm password",
			"enterusername": "Enter user name",

			"minium8": "Minimum of 8 characters required",
			"emailFormat": "Invalid email format",
			"confirmpasswordfail": "Confirm password did not match"
		},
		"privactploicy": "Privacy Policy",
		"termsofservice": "Terms of Service",
		"agreetermnotice": "By signing up, you agree to our",
		"failInLogin": "Failed to Login",
		"failInRegister": "Failed to Register",
		"failInLogout": "Failed to Logout",
		"successfulLogin": "Login successful",
		"successfulRegister": "Register successful",
		"successfulLogout": "Logout successful"
	},
	"and": "and",
	"home": "Home",
	"homedesc": "Monitor all of your projects and tasks here",
	"mytasks": "My Tasks",
	"mytasksdesc": "View all of your tasks here",
	"settings": "Settings",
	"members": "Members",
	"myprojects": "My Project",
	"myprojectsdesc": "View tasks of your project here",
	"form": { "required": "Required", "minium1": "Minimum of 1 characters required" },
	"workspaces": {
		"form": {
			"createTitle": "Create new workspace",
			"name": "Workspace Name",
			"icon": "Workspace Icon",
			"entername": "Enter workspace name",
			"failInCreate": "Failed to create workspaces",
			"succefulCreate": "Workspace created",
			"imageNotice": "JPG, PNG, SVG or jpeg, max 1 mb"
		},
		"switcher": {
			"noselect": "No workspaces selected"
		},
		"name": "Workspaces",
		"dangerzone": {
			"name": "Danger Zone",
			"notice": "Deleting a workspace is irreversible and will remove all associated data.",
			"delete": "Delete Workspace"
		},
		"invitelink": {
			"name": "Invite Members",
			"notice": "Use the invite link to add members to your workspace."
		}
	},
	"cancel": "Cancel",
	"confirm": "Confirm",
	"submit": "Submit",
	"upload": "Upload",
	"delete": "Delete",
	"chooselang": "Choose Lang",
	"back": "Back",
	"savechanges": "Save Changes",
	"canundonotice": "This action cannot be undone."
}
